featurepy/__init__.py
featurepy/feature_class.py
featurepy/flask/__init__.py
featurepy/flask/views.py
featurepy/model_constraints.py
featurepy/parametric_features.py
featurepy/scripts/__init__.py
featurepy/scripts/features.py
featurepy-0.2.5.dist-info/LICENSE
featurepy-0.2.5.dist-info/METADATA
featurepy-0.2.5.dist-info/WHEEL
featurepy-0.2.5.dist-info/entry_points.txt
featurepy-0.2.5.dist-info/RECORD
