Metadata-Version: 2.1
Name: featurepy
Version: 0.2.5
Summary: Framework for building software product lines using feature-oriented programming (FOP) and aspect-oriented programming (AOP) in Python.
Author: Adrian Wong
Author-email: adrianwong227@gmail.com
Requires-Python: >=3.11,<4.0
Classifier: Programming Language :: Python :: 3
Classifier: Programming Language :: Python :: 3.11
Requires-Dist: aspectlib (>=2.0.0,<3.0.0)
Requires-Dist: featuremonkey3 (>=0.1.2,<0.2.0)
Requires-Dist: flask (>=2.3.2,<3.0.0)
Requires-Dist: pyyaml (>=6.0,<7.0)
